backend_base/__init__.py
backend_base/conf/__init__.py
backend_base/conf/global_settings.py
backend_base/exceptions/__init__.py
backend_base/mail/__init__.py
backend_base/mail/message.py
backend_base/mail/utils.py
backend_base/mail/backends/__init__.py
backend_base/mail/backends/base.py
backend_base/mail/backends/console.py
backend_base/mail/backends/dummy.py
backend_base/mail/backends/filebased.py
backend_base/mail/backends/locmem.py
backend_base/mail/backends/smtp.py
backend_base/utils/__init__.py
backend_base/utils/console.py
backend_base/utils/dict.py
backend_base/utils/encoding.py
backend_base/utils/environment.py
backend_base/utils/functional.py
backend_base/utils/module_loading.py
backend_base/utils/string.py
backend_base-0.1.3.dist-info/LICENSE
backend_base-0.1.3.dist-info/METADATA
backend_base-0.1.3.dist-info/WHEEL
backend_base-0.1.3.dist-info/top_level.txt
backend_base-0.1.3.dist-info/RECORD
