Metadata-Version: 2.1
Name: backend-base
Version: 0.1.3
Summary: Backend base package based of some django modules
Home-page: https://github.com/Carlososuna11/backend-base
Author: Carlos Osuna
Author-email: carlosalvaroosuna1@gmail.com
Project-URL: Bug Tracker, https://github.com/Carlososuna11/backend-base/issues
Project-URL: repository, https://github.com/Carlososuna11/backend-base
Classifier: Programming Language :: Python :: 3
Classifier: License :: OSI Approved :: MIT License
Classifier: Operating System :: OS Independent
Requires-Python: >=3.8
License-File: LICENSE
